{"data":{"mtn_sme":[{"id":"1GB","topup_currency":"NGN","topup_amount":400,"price":1000,"data_amount":"1000","validity":"30 days","type":"sme"},{"id":"2GB","topup_currency":"NGN","topup_amount":800,"price":2000,"data_amount":"2000","validity":"30 days","type":"sme"},{"id":"3GB","topup_currency":"NGN","topup_amount":1200,"price":3000,"data_amount":"3000","validity":"30 days","type":"sme"},{"id":"5GB","topup_currency":"NGN","topup_amount":2000,"price":5000,"data_amount":"5000","validity":"30 days","type":"sme"}],"mtn":[]},"time":1595781990}